visidata_mcp/__init__.py
visidata_mcp/server.py
visidata_mcp-0.1.7.dist-info/METADATA
visidata_mcp-0.1.7.dist-info/WHEEL
visidata_mcp-0.1.7.dist-info/entry_points.txt
visidata_mcp-0.1.7.dist-info/licenses/LICENSE
visidata_mcp-0.1.7.dist-info/RECORD
