Metadata-Version: 2.4
Name: visidata-mcp
Version: 0.1.7
Summary: MCP server for VisiData - a terminal spreadsheet multitool for discovering and arranging tabular data
Project-URL: Homepage, https://github.com/moeloubani/visidata-mcp
Project-URL: Repository, https://github.com/moeloubani/visidata-mcp
Author-email: Moe Loubani <moe@moe.ca>
License-File: LICENSE
Classifier: Development Status :: 3 - Alpha
Classifier: Intended Audience :: Developers
Classifier: License :: OSI Approved :: MIT License
Classifier: Programming Language :: Python :: 3
Classifier: Programming Language :: Python :: 3.10
Classifier: Programming Language :: Python :: 3.11
Classifier: Programming Language :: Python :: 3.12
Requires-Python: >=3.10
Requires-Dist: httpx>=0.28.0
Requires-Dist: matplotlib>=3.7.0
Requires-Dist: mcp>=1.9.0
Requires-Dist: numpy>=1.24.0
Requires-Dist: openpyxl>=3.0.0
Requires-Dist: pandas>=2.0.0
Requires-Dist: pillow>=9.0.0
Requires-Dist: scipy>=1.10.0
Requires-Dist: seaborn>=0.12.0
Requires-Dist: visidata>=3.0
